Workbook

Sheet 予実管理
A1: 予実管理表
A3: 売上
A4: No | B4: カテゴリ | C4: 予算額 | D4: 実績額 | E4: 予実対比（円） | F4: 予実対比（%）
A5: 1 | B5: 入場料 | C5: =SUMIF(予算!$B$5:$B$15,予実管理!B5,予算!$G$5:$G$15) -> 440000 | D5: =SUMIF('実績｜売上一覧'!$B$3:$B$52,予実管理!B5,'実績｜売上一覧'!$G$3:$G$52) -> 419500 | E5: =D5-C5 -> -20500 | F5: =D5/C5 -> 0.95340909
A6: 2 | B6: スポンサー料 | C6: =SUMIF(予算!$B$5:$B$14,予実管理!B6,予算!$G$5:$G$14) -> 100000 | D6: =SUMIF('実績｜売上一覧'!$B$3:$B$52,予実管理!B6,'実績｜売上一覧'!$G$3:$G$52) -> 125000 | E6: =D6-C6 -> 25000 | F6: =D6/C6 -> 1.25
A7: 3 | B7: 出展料 | C7: =SUMIF(予算!$B$5:$B$14,予実管理!B7,予算!$G$5:$G$14) -> 90000 | D7: =SUMIF('実績｜売上一覧'!$B$3:$B$52,予実管理!B7,'実績｜売上一覧'!$G$3:$G$52) -> 85000 | E7: =D7-C7 -> -5000 | F7: =D7/C7 -> 0.94444444
A8: 4 | B8: 物販売上 | C8: =SUMIF(予算!$B$5:$B$14,予実管理!B8,予算!$G$5:$G$14) -> 20000 | D8: =SUMIF('実績｜売上一覧'!$B$3:$B$52,予実管理!B8,'実績｜売上一覧'!$G$3:$G$52) -> 26000 | E8: =D8-C8 -> 6000 | F8: =D8/C8 -> 1.3
A9: 5 | B9: その他の売上 | C9: =SUMIF(予算!$B$5:$B$14,予実管理!B9,予算!$G$5:$G$14) -> 0 | D9: =SUMIF('実績｜売上一覧'!$B$3:$B$52,予実管理!B9,'実績｜売上一覧'!$G$3:$G$52) -> 600 | E9: =D9-C9 -> 600 | F9: =D9/C9 -> #DIV/0!
A10: * | B10: 合計 | C10: =SUM(C5:C9) -> 650000 | D10: =SUM(D5:D9) -> 656100 | E10: =D10-C10 -> 6100 | F10: =D10/C10 -> 1.0093846
A12: 支出
A13: No | B13: カテゴリ | C13: 予算額 | D13: 実績額 | E13: 予実対比（円） | F13: 予実対比（%）
A14: 1 | B14: 会場費 | C14: =SUMIF(予算!$B$19:$B$39,予実管理!B14,予算!$G$19:$G$39) -> 125000 | D14: =SUMIF('実績｜経費一覧'!$B$3:$B$52,予実管理!B14,'実績｜経費一覧'!$G$3:$G$52) -> 128000 | E14: =D14-C14 -> 3000 | F14: =D14/C14 -> 1.024
A15: 2 | B15: 人件費 | C15: =SUMIF(予算!$B$19:$B$39,予実管理!B15,予算!$G$19:$G$39) -> 29000 | D15: =SUMIF('実績｜経費一覧'!$B$3:$B$52,予実管理!B15,'実績｜経費一覧'!$G$3:$G$52) -> 51000 | E15: =D15-C15 -> 22000 | F15: =D15/C15 -> 1.7586207
A16: 3 | B16: 制作費 | C16: =SUMIF(予算!$B$19:$B$39,予実管理!B16,予算!$G$19:$G$39) -> 260000 | D16: =SUMIF('実績｜経費一覧'!$B$3:$B$52,予実管理!B16,'実績｜経費一覧'!$G$3:$G$52) -> 272000 | E16: =D16-C16 -> 12000 | F16: =D16/C16 -> 1.0461538
A17: 4 | B17: 広告・宣伝費 | C17: =SUMIF(予算!$B$19:$B$39,予実管理!B17,予算!$G$19:$G$39) -> 81000 | D17: =SUMIF('実績｜経費一覧'!$B$3:$B$52,予実管理!B17,'実績｜経費一覧'!$G$3:$G$52) -> 82000 | E17: =D17-C17 -> 1000 | F17: =D17/C17 -> 1.0123457
A18: 5 | B18: 企画・管理費 | C18: =SUMIF(予算!$B$19:$B$39,予実管理!B18,予算!$G$19:$G$39) -> 55000 | D18: =SUMIF('実績｜経費一覧'!$B$3:$B$52,予実管理!B18,'実績｜経費一覧'!$G$3:$G$52) -> 52400 | E18: =D18-C18 -> -2600 | F18: =D18/C18 -> 0.95272727
A19: 6 | B19: その他の支出 | C19: =SUMIF(予算!$B$19:$B$39,予実管理!B19,予算!$G$19:$G$39) -> 0 | D19: =SUMIF('実績｜経費一覧'!$B$3:$B$52,予実管理!B19,'実績｜経費一覧'!$G$3:$G$52) -> 4000 | E19: =D19-C19 -> 4000 | F19: =D19/C19 -> #DIV/0!
A20: * | B20: 合計 | C20: =SUM(C14:C19) -> 550000 | D20: =SUM(D14:D19) -> 589400 | E20: =D20-C20 -> 39400 | F20: =D20/C20 -> 1.0716364
A22: 収支
A23: * | B23: 売上合計-支出合計 | C23: =C10-C20 -> 100000 | D23: =D10-D20 -> 66700 | E23: =D23-C23 -> -33300 | F23: =D23/C23 -> 0.667

Sheet 予算
A1: イベント収支管理表【予算の部】
A3: 売上
A4: No | B4: カテゴリ | C4: 詳細１ | D4: 詳細２ | E4: 単価 | F4: 数量 | G4: 金額
A5: 1 | B5: 入場料 | C5: チケット | D5: 前売 | E5: 2000 | F5: 100 | G5: =E5*F5 -> 200000
A6: 2 | B6: 入場料 | C6: チケット | D6: 当日 | E6: 2500 | F6: 60 | G6: =E6*F6 -> 150000
A7: 3 | B7: 入場料 | C7: ゲスト | D7: ディスカウント | E7: 1800 | F7: 50 | G7: =E7*F7 -> 90000
A8: 4 | B8: スポンサー料 | C8: 協賛A | E8: 50000 | F8: 1 | G8: =E8*F8 -> 50000
A9: 5 | B9: スポンサー料 | C9: 協賛B | E9: 25000 | F9: 2 | G9: =E9*F9 -> 50000
A10: 6 | B10: 出展料 | C10: ブースA | D10: 1K×1.5Kテント | E10: 5000 | F10: 6 | G10: =E10*F10 -> 30000
A11: 7 | B11: 出展料 | C11: ブースB | D11: 1.5K×2Kテント | E11: 10000 | F11: 3 | G11: =E11*F11 -> 30000
A12: 8 | B12: 出展料 | C12: ブースC | D12: キッチンカー | E12: 15000 | F12: 2 | G12: =E12*F12 -> 30000
A13: 9 | B13: 物販売上 | C13: グッズA | E13: 500 | F13: 20 | G13: =E13*F13 -> 10000
A14: 10 | B14: 物販売上 | C14: グッズB | E14: 1000 | F14: 10 | G14: =E14*F14 -> 10000
A15: * | B15: 合計 | G15: =SUM(G5:G14) -> 650000
A17: 支出
A18: No | B18: カテゴリ | C18: 詳細１ | D18: 詳細２ | E18: 単価 | F18: 数量 | G18: 金額
A19: 1 | B19: 会場費 | C19: 会場レンタル代 | D19: 本番 | E19: 100000 | F19: 1 | G19: =E19 -> 100000
A20: 2 | B20: 会場費 | C20: 会場レンタル代 | D20: 設営・リハーサル | E20: 25000 | F20: 1 | G20: =E20 -> 25000
A21: 3 | B21: 人件費 | C21: 交通誘導代 | D21: 有資格警備員 | E21: 18000 | F21: 1 | G21: =E21 -> 18000
A22: 4 | B22: 人件費 | C22: 会場スタッフ代 | D22: 一般スタッフ | E22: 11000 | F22: 3 | G22: =E22 -> 11000
A23: 5 | B23: 制作費 | C23: 出演料 | D23: ゲストA 出演料 | E23: 40000 | F23: 1 | G23: =E23 -> 40000
A24: 6 | B24: 制作費 | C24: 出演料 | D24: ゲストA 出演料 | E24: 30000 | F24: 1 | G24: =E24 -> 30000
A25: 7 | B25: 制作費 | C25: 機材レンタル代 | D25: 音響追加機器 一式 | E25: 60000 | F25: 1 | G25: =E25 -> 60000
A26: 8 | B26: 制作費 | C26: 機材レンタル代 | D26: 楽器 一式 | E26: 40000 | F26: 1 | G26: =E26 -> 40000
A27: 9 | B27: 制作費 | C27: 機材レンタル代 | D27: 什器等 一式 | E27: 30000 | F27: 1 | G27: =E27 -> 30000
A28: 10 | B28: 制作費 | C28: 消耗品代 | D28: 会場掲出物 一式 | E28: 5000 | F28: 1 | G28: =E28 -> 5000
A29: 11 | B29: 制作費 | C29: 消耗品代 | D29: 受付用備品 一式 | E29: 5000 | F29: 1 | G29: =E29 -> 5000
A30: 12 | B30: 制作費 | C30: 飲食代 | D30: 出演者ケータリング | E30: 25000 | F30: 1 | G30: =E30 -> 25000
... A37: 19 | B37: 企画・管理費 | C37: 会議費 | D37: 飲食店代金 | E37: 5000 | F37: 1 | G37: =E37 -> 5000
A38: 20 | B38: 企画・管理費 | C38: 管理費用 | D38: 支出×10% | E38: =SUM(G19:G37)*0.1 -> 50000 | F38: 1 | G38: =E38 -> 50000
A39: * | B39: 合計 | G39: =SUM(G19:G38) -> 550000
A41: 収支
A42: * | B42: 売上合計-支出合計 | G42: =G15-G39 -> 100000

Sheet 実績｜売上一覧
A1: 売上一覧
A2: No | B2: カテゴリ | C2: 詳細１ | D2: 詳細２ | E2: 単価 | F2: 数量 | G2: 金額
A3: 1 | B3: 入場料 | C3: チケット | D3: 前売 | E3: 2000 | F3: 92 | G3: =E3*F3 -> 184000
A4: 2 | B4: 入場料 | C4: チケット | D4: 当日 | E4: 2500 | F4: 51 | G4: =E4*F4 -> 127500
A5: 3 | B5: 入場料 | C5: ゲスト | D5: ディスカウント | E5: 1800 | F5: 60 | G5: =E5*F5 -> 108000
A6: 4 | B6: スポンサー料 | C6: 協賛A | E6: 50000 | F6: 1 | G6: =E6*F6 -> 50000
A7: 5 | B7: スポンサー料 | C7: 協賛B | E7: 25000 | F7: 3 | G7: =E7*F7 -> 75000
A8: 6 | B8: 出展料 | C8: ブースA | D8: 1K×1.5Kテント | E8: 5000 | F8: 5 | G8: =E8*F8 -> 25000
A9: 7 | B9: 出展料 | C9: ブースB | D9: 1.5K×2Kテント | E9: 10000 | F9: 3 | G9: =E9*F9 -> 30000
A10: 8 | B10: 出展料 | C10: ブースC | D10: キッチンカー | E10: 15000 | F10: 2 | G10: =E10*F10 -> 30000
A11: 9 | B11: 物販売上 | C11: グッズA | E11: 500 | F11: 22 | G11: =E11*F11 -> 11000
A12: 10 | B12: 物販売上 | C12: グッズB | E12: 1000 | F12: 15 | G12: =E12*F12 -> 15000
A13: 11 | B13: その他の売上 | C13: カンパ | D13: 来場者投げ銭 | E13: 600 | F13: 1 | G13: =E13*F13 -> 600
A14: 12 | G14: =E14*F14 -> 0
A15: 13 | G15: =E15*F15 -> 0
A16: 14 | G16: =E16*F16 -> 0
A17: 15 | G17: =E17*F17 -> 0
A18: 16 | G18: =E18*F18 -> 0
A19: 17 | G19: =E19*F19 -> 0
A20: 18 | G20: =E20*F20 -> 0
A21: 19 | G21: =E21*F21 -> 0
A22: 20 | G22: =E22*F22 -> 0
A23: 21 | G23: =E23*F23 -> 0
A24: 22 | G24: =E24*F24 -> 0
A25: 23 | G25: =E25*F25 -> 0
... A52: 50 | G52: =E52*F52 -> 0

Sheet 実績｜経費一覧
A1: 経費一覧
A2: No | B2: カテゴリ | C2: 詳細１ | D2: 詳細２ | E2: 単価 | F2: 数量 | G2: 金額 | H2: 支払先[メモ] | I2: 支払期限[メモ] | J2: 支出状況
A3: 1 | B3: 会場費 | C3: 会場レンタル代 | D3: 本番 | E3: 100000 | F3: 1 | G3: =E3*F3 -> 100000
A4: 2 | B4: 会場費 | C4: 会場レンタル代 | D4: 設営・リハーサル | E4: 28000 | F4: 1 | G4: =E4*F4 -> 28000
A5: 3 | B5: 人件費 | C5: 交通誘導代 | D5: 有資格警備員 | E5: 18000 | F5: 1 | G5: =E5*F5 -> 18000
A6: 4 | B6: 人件費 | C6: 会場スタッフ代 | D6: 一般スタッフ | E6: 11000 | F6: 3 | G6: =E6*F6 -> 33000
A7: 5 | B7: 制作費 | C7: 出演料 | D7: ゲストA 出演料 | E7: 44000 | F7: 1 | G7: =E7*F7 -> 44000
A8: 6 | B8: 制作費 | D8: ゲストA 出演料 | E8: 33000 | F8: 1 | G8: =E8*F8 -> 33000
A9: 7 | B9: 制作費 | C9: 機材レンタル代 | D9: 音響追加機器 一式 | E9: 65000 | F9: 1 | G9: =E9*F9 -> 65000
A10: 8 | B10: 制作費 | D10: 楽器 一式 | E10: 40000 | F10: 1 | G10: =E10*F10 -> 40000
A11: 9 | B11: 制作費 | D11: 什器等 一式 | E11: 30000 | F11: 1 | G11: =E11*F11 -> 30000
A12: 10 | B12: 制作費 | C12: 消耗品代 | D12: 会場掲出物 一式 | E12: 5000 | F12: 1 | G12: =E12*F12 -> 5000
A13: 11 | B13: 制作費 | D13: 受付用備品 一式 | E13: 5000 | F13: 1 | G13: =E13*F13 -> 5000
A14: 12 | B14: 制作費 | C14: 飲食代 | D14: 出演者ケータリング | E14: 25000 | F14: 1 | G14: =E14*F14 -> 25000
A15: 13 | B15: 制作費 | D15: スタッフ弁当・飲料 | E15: 15000 | F15: 1 | G15: =E15*F15 -> 15000
A16: 14 | B16: 制作費 | C16: 交通費 | D16: タクシー代 | E16: 10000 | F16: 1 | G16: =E16*F16 -> 10000
A17: 15 | B17: 広告・宣伝費 | C17: デザイン費 | D17: キービジュアル制作 | E17: 27500 | F17: 1 | G17: =E17*F17 -> 27500
A18: 16 | B18: 広告・宣伝費 | D18: ポスターデザイン | E18: 14800 | F18: 1 | G18: =E18*F18 -> 14800
A19: 17 | B19: 広告・宣伝費 | C19: 印刷費 | D19: チラシ・ポスター | E19: 9900 | F19: 1 | G19: =E19*F19 -> 9900
A20: 18 | B20: 広告・宣伝費 | C20: Web関係費 | D20: HP制作・管理 | E20: 29800 | F20: 1 | G20: =E20*F20 -> 29800
A21: 19 | B21: 企画・管理費 | C21: 会議費 | D21: 飲食店代金 | E21: 2400 | F21: 1 | G21: =E21*F21 -> 2400
A22: 20 | B22: 企画・管理費 | C22: 管理費用 | E22: 50000 | F22: 1 | G22: =E22*F22 -> 50000
A23: 21 | B23: その他の支出 | C23: 保険代 | D23: 損害賠償保険 | E23: 4000 | F23: 1 | G23: =E23*F23 -> 4000
A24: 22 | G24: =E24*F24 -> 0
A25: 23 | G25: =E25*F25 -> 0
A26: 24 | G26: =E26*F26 -> 0
A27: 25 | G27: =E27*F27 -> 0
A28: 26 | G28: =E28*F28 -> 0
A29: 27 | G29: =E29*F29 -> 0
A30: 28 | G30: =E30*F30 -> 0
A31: 29 | G31: =E31*F31 -> 0
A32: 30 | G32: =E32*F32 -> 0
A33: 31 | G33: =E33*F33 -> 0
A34: 32 | G34: =E34*F34 -> 0
A35: 33 | G35: =E35*F35 -> 0
... A52: 50 | G52: =E52*F52 -> 0

Sheet 入力規制
A1: 支出カテゴリ
A2: 会場費
A3: 人件費
A4: 制作費
A5: 広告・宣伝費
A6: 企画・管理費
A7: その他の支出
A9: 売上カテゴリ
A10: 入場料
A11: スポンサー料
A12: 出展料
A13: 物販売上
... A22: 受取り済
